rio_config/__init__.py
rio_config/functions.py
rio_config-0.1.3.dist-info/METADATA
rio_config-0.1.3.dist-info/WHEEL
rio_config-0.1.3.dist-info/top_level.txt
rio_config-0.1.3.dist-info/RECORD
