Metadata-Version: 2.4
Name: rio_config
Version: 0.1.3
Summary: Rio configuration parser
Author-email: Mike Reider <mike.reider@gmail.com>
License: MIT
Project-URL: Homepage, https://github.com/perfecto25/rio_config
Keywords: rio_config
Classifier: Programming Language :: Python :: 3
Classifier: Operating System :: OS Independent
Requires-Python: >=3.6
